seeed_python_reterminal/__init__.py
seeed_python_reterminal/acceleration.py
seeed_python_reterminal/button.py
seeed_python_reterminal/core.py
seeed_python_reterminal-0.5.dist-info/LICENSE
seeed_python_reterminal-0.5.dist-info/METADATA
seeed_python_reterminal-0.5.dist-info/WHEEL
seeed_python_reterminal-0.5.dist-info/top_level.txt
seeed_python_reterminal-0.5.dist-info/RECORD
